ramo/__init__.py
ramo/commitment/__init__.py
ramo/commitment/best_response.py
ramo/commitment/comp_action.py
ramo/commitment/coop_action.py
ramo/commitment/coop_policy.py
ramo/commitment/execute_commitment.py
ramo/commitment/non_stationary.py
ramo/commitment/optional_com.py
ramo/game/__init__.py
ramo/game/checking.py
ramo/game/example_games.py
ramo/game/generators.py
ramo/game/monfg.py
ramo/game/monfgs.py
ramo/game/properties.py
ramo/learner/__init__.py
ramo/learner/execute_learner.py
ramo/learner/indep_actor_critic.py
ramo/learner/indep_q.py
ramo/learner/ja_actor_critic.py
ramo/learner/ja_q.py
ramo/nash/IBR.py
ramo/nash/Player.py
ramo/nash/__init__.py
ramo/nash/execute_algorithm.py
ramo/nash/fictitious_play.py
ramo/nash/moqups.py
ramo/nash/mose.py
ramo/nash/verify.py
ramo/pareto/__init__.py
ramo/pareto/dominance.py
ramo/pareto/pareto_nash.py
ramo/pareto/verify.py
ramo/printing/__init__.py
ramo/printing/printing.py
ramo/strategy/__init__.py
ramo/strategy/best_response.py
ramo/strategy/operations.py
ramo/strategy/strategies.py
ramo/utility_function/__init__.py
ramo/utility_function/checking.py
ramo/utility_function/functions.py
ramo/utility_function/generators.py
ramo/utils/__init__.py
ramo/utils/agent_loader.py
ramo/utils/data.py
ramo/utils/experiments.py
ramo/utils/helpers.py
ramo-0.1.3.dist-info/LICENSE
ramo-0.1.3.dist-info/METADATA
ramo-0.1.3.dist-info/WHEEL
ramo-0.1.3.dist-info/top_level.txt
ramo-0.1.3.dist-info/RECORD
