Metadata-Version: 2.1
Name: ramo
Version: 0.1.3
Summary: Algorithms for computing or learning equilibria in multi-objective games
Author: Willem Röpke
Author-email: willem.ropke@vub.be
Classifier: Programming Language :: Python :: 3
Classifier: License :: OSI Approved :: MIT License
Classifier: Operating System :: OS Independent
Requires-Python: >=3.6
License-File: LICENSE
